kijiji/__init__.py
kijiji-0.0.1.dist-info/LICENSE
kijiji-0.0.1.dist-info/WHEEL
kijiji-0.0.1.dist-info/METADATA
kijiji-0.0.1.dist-info/RECORD
